{
  "id": "sec-5-2",
  "number": "7.3тАУ7.4",
  "title": "Run-Length & Huffman Coding",
  "content": [
    {
      "type": "markdown",
      "body": "## Run-Length Coding (RLC)\n\nтЬЕ Data has **long runs** (same value repeats)\nтЭМ Data alternates (010101...)\n\nInstead of storing each bit: store **symbol** + **count**\n\n**Example:**\n\n```\nOriginal:  0000001111110000000000111\nEncoded:   (0, 6), (1, 7), (0, 10), (1, 3)\n```\n\n\"Six 0s, then seven 1s, then ten 0s, then three 1s\"\n\nBest for: scanned documents, binary images with large uniform regions\n\n---\n\n## Huffman Coding\n\nтЬЕ Short codes тЖТ common symbols\nтЬЕ Long codes тЖТ rare symbols\nтЖТ Fewer bits on average\n\n### Algorithm (6 steps)\n\n1. **Count** frequencies\n2. **Sort** (smallest first)\n3. **Build tree** (combine two smallest, repeat)\n4. **Read codes** (left=0, right=1)\n5. **Encode** (replace letters with codes)\n6. **Decode** (walk tree bit by bit)\n\n---\n\n## Worked Example: \"banana\"\n\n### Step 1 тАФ Count\n```\nb тЖТ 1\nn тЖТ 2\na тЖТ 3\n```\n\n### Step 2 тАФ Sort\n```\nb: 1,  n: 2,  a: 3\n```\n\n### Step 3 тАФ Build tree\n\nPick two smallest (b=1, n=2):\n```\n    (3)\n   /   \\\n  b     n\n```\n\nPick (3) + a(3):\n```\n       (6)\n      /   \\\n    (3)    a\n   /   \\\n  b     n\n```\n\n### Step 4 тАФ Read codes\n* **a:** right тЖТ **1**\n* **b:** left, left тЖТ **00**\n* **n:** left, right тЖТ **01**\n\n### Step 5 тАФ Encode\n```\nb  a  n  a  n  a\n00  1 01  1 01  1\n```\nResult: **001011011** (9 bits) тАФ Compare: 6 chars ├Ч 8 bits = 48 bits тЖТ saved 39 bits!\n\n### Step 6 тАФ Decode \"001011011\"\n```\n0,0 тЖТ b\n1   тЖТ a\n0,1 тЖТ n\n1   тЖТ a\n0,1 тЖТ n\n1   тЖТ a\n```\nOutput: **banana** тЬУ\n\n---\n\n## Performance calculation\n\n```\na: 3/6 ├Ч 1 bit  = 0.5\nn: 2/6 ├Ч 2 bits = 0.66\nb: 1/6 ├Ч 2 bits = 0.34\n```\n\nl╠Д = **1.5 bits/symbol**\n\n```\nH = -(0.5├ЧlogтВВ0.5) - (0.33├ЧlogтВВ0.33) - (0.17├ЧlogтВВ0.17)\nH тЙИ 1.459 bits/symbol\n```\n\n**Check:** H тЙд l╠Д < H+1 тЖТ 1.459 тЙд 1.5 < 2.459 тЬУ"
    }
  ],
  "flashcards": [
    {
      "q": "What is Run-Length Coding and when does it fail?",
      "a": "Stores symbol + how many times it repeats instead of every individual value. Best for long runs (e.g., scanned documents). Worst case: alternating data like 010101 тАФ RLC makes it bigger."
    },
    {
      "q": "Describe the Huffman coding algorithm step by step.",
      "a": "1. Count frequencies, sort least to most. 2. Pick two smallest, merge (sum frequencies), add back to list. 3. Repeat until one root. 4. Trace root-to-leaf: left=0, right=1. 5. Encode by replacing symbols with codes. 6. Decode by walking tree bit by bit, output leaf symbols."
    },
    {
      "q": "In Huffman coding of 'banana', what codes are assigned?",
      "a": "a=1 (1 bit), b=00 (2 bits), n=01 (2 bits). 'a' is most frequent so it gets the shortest code. Encoding 'banana' = 001011011 = 9 bits (vs 48 bits in 8-bit ASCII). CR = 5.33."
    },
    {
      "q": "In Huffman coding of 'ABRACADABRA', what code is assigned to A?",
      "a": "A=0 (just 1 bit). A appears 5 out of 11 times тАФ nearly half тАФ so it gets the shortest possible code. All other symbols (B,R,C,D) get 3-bit codes."
    },
    {
      "q": "What is the Unique Prefix Property of Huffman codes?",
      "a": "No Huffman code is a prefix of any other. This means decoding is always unambiguous тАФ you always know exactly when one codeword ends and the next begins."
    },
    {
      "q": "What is the Huffman optimality guarantee?",
      "a": "H тЙд l╠Д < H + 1. Huffman is always within 1 bit of entropy. The two least-frequent symbols always have the same code length in any Huffman tree."
    },
    {
      "q": "What is Extended Huffman Coding?",
      "a": "Group k symbols together and code them as one unit. Reduces the overhead from H+1 to H+1/k. But the alphabet size explodes to n^k, making it impractical for large k."
    }
  ],
  "problems": [
    {
      "type": "calculation",
      "q": "Build the full Huffman tree for \"banana\" (a=3, n=2, b=1). List codes, compute $\\bar{l}$, entropy $H$, and verify $H \\leq \\bar{l} < H+1$.",
      "a": "**Tree:** Merge b(1)+n(2)тЖТ(3), then (3)+a(3)тЖТroot(6)\n\n**Codes:** a=**1**, b=**00**, n=**01**\n\n**$\\bar{l}$** = 0.5├Ч1 + 0.333├Ч2 + 0.167├Ч2 = **1.5** bits/symbol\n\n**H** тЙИ 1.459 bits/symbol\n\n**Check:** 1.459 тЙд 1.5 < 2.459 тЬУ",
      "hint": "Always merge the two smallest nodes. Left=0, right=1 from root to leaf."
    },
    {
      "type": "calculation",
      "q": "Build the Huffman tree for \"mississippi\" (i=4, s=4, p=2, m=1). List all codes and compute $\\bar{l}$.",
      "a": "**Merges:** m(1)+p(2)тЖТ(3), then (3)+s(4)тЖТ(7), then (7)+i(4)тЖТroot(11)\n\n**Codes:** i=**1**, s=**01**, p=**001**, m=**000**\n\n**$\\bar{l}$** = (4/11)├Ч1 + (4/11)├Ч2 + (2/11)├Ч3 + (1/11)├Ч3\n= 0.36 + 0.73 + 0.55 + 0.27 = **1.91** bits/symbol\n\nOriginal: 11├Ч8=88 bits тЖТ Huffman: 21 bits",
      "hint": "When frequencies tie (i=4, s=4), either order works. Most frequent gets shortest code."
    },
    {
      "type": "calculation",
      "q": "Build the Huffman tree for \"aaabbc\" (a=3, b=2, c=1). List codes and encode the string.",
      "a": "**Merges:** c(1)+b(2)тЖТ(3), then (3)+a(3)тЖТroot(6)\n\n**Codes:** a=**1**, b=**01**, c=**00**\n\n**Encode \"aaabbc\":**\n```\na  a  a  b  b  c\n1  1  1  01 01 00\n```\nResult: **111010100** (9 bits)\n\nMost frequent symbol (a) gets shortest code (1 bit) тЬУ",
      "hint": "Same structure as \"banana\" тАФ most frequent always gets shortest code."
    },
    {
      "type": "conceptual",
      "q": "Build the Huffman tree for \"abcd\" where all 4 symbols appear exactly once. What is $\\bar{l}$, and why is there no real compression gain?",
      "a": "**Merges:** a(1)+b(1)тЖТ(2), c(1)+d(1)тЖТ(2), then (2)+(2)тЖТroot(4)\n\n**Codes:** a=00, b=01, c=10, d=11 тАФ all 2 bits\n\n**$\\bar{l}$** = 2 bits/symbol\n\nNo compression gain because $H = \\log_2(4) = 2$ bits тАФ uniform distribution is already at the entropy floor. Huffman cannot compress further.",
      "hint": "Uniform distribution = maximum entropy. Huffman still works, but $\\bar{l} = H$ тАФ no gain over fixed-length coding."
    },
    {
      "type": "calculation",
      "q": "Decode the bit string \"001011011\" using the \"banana\" Huffman tree (a=1, b=00, n=01).",
      "a": "Walk the tree bit by bit, restart at root after each symbol:\n\n0,0 тЖТ **b** | 1 тЖТ **a** | 0,1 тЖТ **n** | 1 тЖТ **a** | 0,1 тЖТ **n** | 1 тЖТ **a**\n\nResult: **banana** тЬУ",
      "hint": "When you reach a leaf, output that symbol and immediately restart from the root."
    }
  ]
}